ai_audit/__init__.py
ai_audit/ai_auditor.py
ai_audit/auditor.py
ai_audit/cli.py
ai_audit/exceptions.py
ai_audit/assessors/vulnerability_assessor.py
ai_audit/collectors/dependency_collector.py
ai_audit/models/ai_domain.py
ai_audit/models/ai_model_config.py
ai_audit/models/dependency.py
ai_audit/models/vulnerability.py
ai_audit/services/vulnerability_service.py
ai_audit_tool-0.2.0.dist-info/licenses/LICENSE
ai_audit_tool-0.2.0.dist-info/METADATA
ai_audit_tool-0.2.0.dist-info/WHEEL
ai_audit_tool-0.2.0.dist-info/entry_points.txt
ai_audit_tool-0.2.0.dist-info/top_level.txt
ai_audit_tool-0.2.0.dist-info/RECORD
