Metadata-Version: 2.4
Name: ai-audit-tool
Version: 0.2.0
Summary: AI包漏洞审计工具，支持命令行和模块调用
Author-email: 奋进的小杨 <2207862552@qq.com>
Classifier: Programming Language :: Python :: 3
Classifier: License :: OSI Approved :: MIT License
Classifier: Operating System :: OS Independent
Requires-Python: >=3.8
License-File: LICENSE
Requires-Dist: requests>=2.31.0
Requires-Dist: toml>=0.10.2
Requires-Dist: python-dateutil>=2.8.2
Provides-Extra: ai
Requires-Dist: openai>=1.0.0; extra == "ai"
Dynamic: license-file
